{
  "title": "Gry BeeMentor",
  "subtitle": "Gry edukacyjne dla początkujących pszczelarzy",
  "levelMap": "Mapa poziomów",
  "earnedBadges": "Odblokowane odznaki",
  "badgesCollection": "Moja kolekcja",
  "courseOffer": "Chcę cały kurs \"Pierwszy rok z pszczołami\"",
  "strength": "Siła rodziny",
  "supplies": "Zapasy",
  "swarming": "Rojliwość",
  "honeyYield": "Miód",
  "month": "Miesiąc",
  "swarmedAlertTitle": "Rójka!",
  "swarmedAlertDesc": "Rojliwość osiągnęła 100%. Pszczoły wyroiły się. Siła spadła o 30, zapasy i miód spadły, rojliwość spadła do 40%.",
  "gameOverTitle": "Koniec gry: Ul nie przeżył",
  "gameOverDesc": "Siła rodziny lub zapasy spadły do zera. Spróbuj ponownie i uratuj swój ul!",
  "finalYield": "Wydajność końcowa",
  "playAgain": "Zagraj ponownie",
  "shareResult": "Udostępnij wynik",
  "shareMessage": "Śledź mój wynik na BeeMentor!",
  "downloadImage": "Pobierz obraz",
  "close": "Zamknij",
  "backToMap": "Powrót do mapy",
  "correctTitle": "Dobrze!",
  "wrongTitle": "Błąd!",
  "continue": "Kontynuuj",
  "finish": "Zakończ",
  "score": "Wynik",
  "bestScore": "Najlepszy wynik",
  "locked": "Zablokowane",
  "questionLabel": "Pytanie {n} z {m}",
  "emailGateTitle": "Odblokuj następny poziom za darmo",
  "emailGateDesc": "Zostaw nam swój e-mail i kontynuuj. Bez spamu — tylko wskazówki pszczelarskie.",
  "emailPlaceholder": "pszczelarz@email.pl",
  "unlockBtn": "Odblokuj",
  "extraTopicsTitle": "Tematy",
  "levelCompleted": "Poziom ukończony!",
  "attempts": "Próby",
  "newBadgeUnlocked": "Nowa odznaka odblokowana!",
  "nextLevel": "Kontynuuj do następnego poziomu →",
  "praises": {
    "correct": [
      "Dokładnie tak!",
      "Masz to w małym palcu.",
      "Pszczoły by ci zaklaskały.",
      "Jak doświadczony pszczelarz.",
      "Bez wahania.",
      "To był rarytas.",
      "Matka byłaby dumna.",
      "Czysta robota.",
      "Jak w zegarku.",
      "Za pierwszym razem."
    ],
    "wrong": [
      "Nie szkodzi, teraz już wiesz.",
      "Nawet doświadczeni pszczelarze uczą się co sezon.",
      "Błąd w aplikacji jest lepszy niż błąd przy ulu.",
      "Właśnie się czegoś nauczyłeś – to cel gry.",
      "Każdy błąd przybliża cię do mistrzostwa."
    ],
    "streak3": "Trzy z rzędu – rozkręcasz się!",
    "streak5": "Pięć z rzędu! Jesteś w swoim żywiole.",
    "streak10": "Dziesięć z rzędu – to jest mistrzowski przegląd!"
  }
}
